airflow/hooks/glue_presto_apas.py
airflow/operators/glue_add_partition.py
airflow/operators/glue_presto_apas.py
airflow/plugins/glue_presto_apas.py
airflow_plugin_glue_presto_apas-0.0.11.dist-info/entry_points.txt
airflow_plugin_glue_presto_apas-0.0.11.dist-info/LICENSE.txt
airflow_plugin_glue_presto_apas-0.0.11.dist-info/WHEEL
airflow_plugin_glue_presto_apas-0.0.11.dist-info/METADATA
airflow_plugin_glue_presto_apas-0.0.11.dist-info/RECORD
