Metadata-Version: 2.1
Name: airflow-plugin-glue-presto-apas
Version: 0.0.11
Summary: An Airflow Plugin to Add a Partition As Select(APAS) on Presto that uses Glue Data Catalog as a Hive metastore.
Home-page: https://github.com/civitaspo/airflow-plugin-glue_presto_apas
License: UNKNOWN
Author: Civitaspo
Author-email: civitaspo@gmail.com
Requires-Python: >=3.6,<4.0
Classifier: Development Status :: 4 - Beta
Classifier: Programming Language :: Python :: 3
Classifier: Programming Language :: Python :: 3.6
Classifier: Programming Language :: Python :: 3.7
Requires-Dist: apache-airflow (>=1.10,<2.0)
Requires-Dist: presto-python-client (>=0.5.1,<0.6.0)
Project-URL: Repository, https://github.com/civitaspo/airflow-plugin-glue_presto_apas
